README.md
setup.cfg
setup.py
yarb/__init__.py
yarb/yarb.py
yarb.egg-info/PKG-INFO
yarb.egg-info/SOURCES.txt
yarb.egg-info/dependency_links.txt
yarb.egg-info/entry_points.txt
yarb.egg-info/requires.txt
yarb.egg-info/top_level.txt