Metadata-Version: 1.1
Name: yarb
Version: 1.0.0
Summary: Yet Another Rabbit Balancer
Home-page: https://github.com/Itxaka/yarb
Author: Itxaka Serrano Garcia
Author-email: igarcia@suse.com
License: GPL2.0
Platform: UNKNOWN
Classifier: Programming Language :: Python
Classifier: Programming Language :: Python :: 2.7
Classifier: Programming Language :: Python :: 3
Classifier: Programming Language :: Python :: 3.3
Classifier: Programming Language :: Python :: 3.4
Classifier: Programming Language :: Python :: 3.5
Classifier: Programming Language :: Python :: 3.6
Classifier: Environment :: Console
